{
    "W1": "abs",
    "W2": "begin",
    "W3": "cos",
    "W4": "do",
    "W5": "downto",
    "W6": "else",
    "W7": "end",
    "W8": "exp",
    "W9": "for",
    "W10": "function",
    "W11": "goto",
    "W12": "if",
    "W13": "integer",
    "W14": "ln",
    "W15": "of",
    "W16": "procedure",
    "W17": "program",
    "W18": "read",
    "W19": "readln",
    "W20": "real",
    "W21": "repeat",
    "W22": "sin",
    "W23": "sqrt",
    "W24": "string",
    "W25": "then",
    "W26": "to",
    "W27": "until",
    "W28": "var",
    "W29": "while",
    "W30": "write",
    "W31": "writeln"
}